MANIFEST.in
README.txt
setup.cfg
setup.py
collective/__init__.py
collective.cdn.multiplehostnames.egg-info/PKG-INFO
collective.cdn.multiplehostnames.egg-info/SOURCES.txt
collective.cdn.multiplehostnames.egg-info/dependency_links.txt
collective.cdn.multiplehostnames.egg-info/entry_points.txt
collective.cdn.multiplehostnames.egg-info/namespace_packages.txt
collective.cdn.multiplehostnames.egg-info/not-zip-safe
collective.cdn.multiplehostnames.egg-info/requires.txt
collective.cdn.multiplehostnames.egg-info/top_level.txt
collective/cdn/__init__.py
collective/cdn/multiplehostnames/README.txt
collective/cdn/multiplehostnames/__init__.py
collective/cdn/multiplehostnames/config.py
collective/cdn/multiplehostnames/configure.zcml
collective/cdn/multiplehostnames/provider.py
collective/cdn/multiplehostnames/testing.py
collective/cdn/multiplehostnames/version.txt
collective/cdn/multiplehostnames/docs/__init__.py
collective/cdn/multiplehostnames/docs/browser.txt
collective/cdn/multiplehostnames/tests/__init__.py
collective/cdn/multiplehostnames/tests/test_funcional.py
docs/HISTORY.txt
docs/INSTALL.txt
docs/LICENSE.GPL
docs/LICENSE.txt